{"v":"4.8.0","meta":{"g":"LottieFiles AE 3.5.7","a":"","k":"","d":"","tc":""},"fr":24,"ip":0,"op":216,"w":900,"h":900,"nm":"Globos","ddd":0,"assets":[],"layers":[{"ddd":0,"ind":1,"ty":4,"nm":"Capa de formas 36","sr":1,"ks":{"o":{"a":0,"k":100,"ix":11},"r":{"a":0,"k":180,"ix":10},"p":{"a":0,"k":[201,704,0],"ix":2},"a":{"a":0,"k":[257,271,0],"ix":1},"s":{"a":0,"k":[100,-100,100],"ix":6}},"ao":0,"shapes":[{"ty":"gr","it":[{"ind":0,"ty":"sh","ix":1,"ks":{"a":0,"k":{"i":[[0,0],[34.404,31.652],[35.569,35.967],[42.643,32.385],[50.688,33.951],[39.992,25.316],[42.045,22.945],[98,-18]],"o":[[0,0],[-37.227,-34.248],[-37.652,-38.073],[-48.586,-36.898],[-39.325,-26.34],[-53.232,-33.697],[-71.219,-38.867],[-86,-28]],"v":[[245,255],[195,157],[70,94],[0,-28],[-142,-67],[-218,-183],[-360,-205],[-546,-362]],"c":false},"ix":2},"nm":"Trazado 1","mn":"ADBE Vector Shape - Group","hd":false},{"ty":"st","c":{"a":0,"k":[1,1,1,1],"ix":3},"o":{"a":0,"k":100,"ix":4},"w":{"a":0,"k":16,"ix":5},"lc":2,"lj":2,"bm":0,"nm":"Trazo 1","mn":"ADBE Vector Graphic - Stroke","hd":false},{"ty":"tr","p":{"a":0,"k":[0,0],"ix":2},"a":{"a":0,"k":[0,0],"ix":1},"s":{"a":0,"k":[104.858,106.226],"ix":3},"r":{"a":0,"k":0,"ix":6},"o":{"a":0,"k":100,"ix":7},"sk":{"a":0,"k":0,"ix":4},"sa":{"a":0,"k":0,"ix":5},"nm":"Transformar"}],"nm":"Forma 1","np":3,"cix":2,"bm":0,"ix":1,"mn":"ADBE Vector Group","hd":false},{"ty":"tm","s":{"a":1,"k":[{"i":{"x":[0.667],"y":[1]},"o":{"x":[0.167],"y":[0.167]},"t":133,"s":[0]},{"t":161,"s":[100]}],"ix":1},"e":{"a":1,"k":[{"i":{"x":[0.833],"y":[0.833]},"o":{"x":[0.167],"y":[0.167]},"t":133,"s":[0]},{"i":{"x":[0.667],"y":[1]},"o":{"x":[0.167],"y":[0.167]},"t":143,"s":[15]},{"t":161,"s":[100]}],"ix":2},"o":{"a":0,"k":0,"ix":3},"m":1,"ix":2,"nm":"Recortar trazados 1","mn":"ADBE Vector Filter - Trim","hd":false}],"ip":133,"op":220,"st":4,"bm":0},{"ddd":0,"ind":2,"ty":4,"nm":"Capa de formas 35","sr":1,"ks":{"o":{"a":0,"k":100,"ix":11},"r":{"a":0,"k":20,"ix":10},"p":{"a":0,"k":[215,713,0],"ix":2},"a":{"a":0,"k":[257,271,0],"ix":1},"s":{"a":0,"k":[-100,100,100],"ix":6}},"ao":0,"shapes":[{"ty":"gr","it":[{"ind":0,"ty":"sh","ix":1,"ks":{"a":0,"k":{"i":[[0,0],[34.404,31.652],[35.569,35.967],[42.643,32.385],[50.688,33.951],[39.992,25.316],[42.045,22.945],[98,-18]],"o":[[0,0],[-37.227,-34.248],[-37.652,-38.073],[-48.586,-36.898],[-39.325,-26.34],[-53.232,-33.697],[-71.219,-38.867],[-86,-28]],"v":[[245,255],[195,157],[70,94],[0,-28],[-142,-67],[-218,-183],[-360,-205],[-546,-362]],"c":false},"ix":2},"nm":"Trazado 1","mn":"ADBE Vector Shape - Group","hd":false},{"ty":"st","c":{"a":0,"k":[1,1,1,1],"ix":3},"o":{"a":0,"k":100,"ix":4},"w":{"a":0,"k":16,"ix":5},"lc":2,"lj":2,"bm":0,"nm":"Trazo 1","mn":"ADBE Vector Graphic - Stroke","hd":false},{"ty":"tr","p":{"a":0,"k":[0,0],"ix":2},"a":{"a":0,"k":[0,0],"ix":1},"s":{"a":0,"k":[104.858,106.226],"ix":3},"r":{"a":0,"k":0,"ix":6},"o":{"a":0,"k":100,"ix":7},"sk":{"a":0,"k":0,"ix":4},"sa":{"a":0,"k":0,"ix":5},"nm":"Transformar"}],"nm":"Forma 1","np":3,"cix":2,"bm":0,"ix":1,"mn":"ADBE Vector Group","hd":false},{"ty":"tm","s":{"a":1,"k":[{"i":{"x":[0.667],"y":[1]},"o":{"x":[0.167],"y":[0.167]},"t":135,"s":[0]},{"t":163,"s":[100]}],"ix":1},"e":{"a":1,"k":[{"i":{"x":[0.833],"y":[0.833]},"o":{"x":[0.167],"y":[0.167]},"t":135,"s":[0]},{"i":{"x":[0.667],"y":[1]},"o":{"x":[0.167],"y":[0.167]},"t":145,"s":[15]},{"t":163,"s":[100]}],"ix":2},"o":{"a":0,"k":0,"ix":3},"m":1,"ix":2,"nm":"Recortar trazados 1","mn":"ADBE Vector Filter - Trim","hd":false}],"ip":135,"op":222,"st":6,"bm":0},{"ddd":0,"ind":3,"ty":4,"nm":"Capa de formas 34","sr":1,"ks":{"o":{"a":0,"k":100,"ix":11},"r":{"a":0,"k":-18,"ix":10},"p":{"a":0,"k":[218,721,0],"ix":2},"a":{"a":0,"k":[257,271,0],"ix":1},"s":{"a":0,"k":[-100,100,100],"ix":6}},"ao":0,"shapes":[{"ty":"gr","it":[{"ind":0,"ty":"sh","ix":1,"ks":{"a":0,"k":{"i":[[0,0],[34.404,31.652],[35.569,35.967],[42.643,32.385],[50.688,33.951],[39.992,25.316],[42.045,22.945],[98,-18]],"o":[[0,0],[-37.227,-34.248],[-37.652,-38.073],[-48.586,-36.898],[-39.325,-26.34],[-53.232,-33.697],[-71.219,-38.867],[-86,-28]],"v":[[245,255],[195,157],[70,94],[0,-28],[-142,-67],[-218,-183],[-360,-205],[-546,-362]],"c":false},"ix":2},"nm":"Trazado 1","mn":"ADBE Vector Shape - Group","hd":false},{"ty":"st","c":{"a":0,"k":[1,1,1,1],"ix":3},"o":{"a":0,"k":100,"ix":4},"w":{"a":0,"k":16,"ix":5},"lc":2,"lj":2,"bm":0,"nm":"Trazo 1","mn":"ADBE Vector Graphic - Stroke","hd":false},{"ty":"tr","p":{"a":0,"k":[0,0],"ix":2},"a":{"a":0,"k":[0,0],"ix":1},"s":{"a":0,"k":[104.858,106.226],"ix":3},"r":{"a":0,"k":0,"ix":6},"o":{"a":0,"k":100,"ix":7},"sk":{"a":0,"k":0,"ix":4},"sa":{"a":0,"k":0,"ix":5},"nm":"Transformar"}],"nm":"Forma 1","np":3,"cix":2,"bm":0,"ix":1,"mn":"ADBE Vector Group","hd":false},{"ty":"tm","s":{"a":1,"k":[{"i":{"x":[0.667],"y":[1]},"o":{"x":[0.167],"y":[0.167]},"t":133,"s":[0]},{"t":161,"s":[100]}],"ix":1},"e":{"a":1,"k":[{"i":{"x":[0.833],"y":[0.833]},"o":{"x":[0.167],"y":[0.167]},"t":133,"s":[0]},{"i":{"x":[0.667],"y":[1]},"o":{"x":[0.167],"y":[0.167]},"t":143,"s":[15]},{"t":161,"s":[100]}],"ix":2},"o":{"a":0,"k":0,"ix":3},"m":1,"ix":2,"nm":"Recortar trazados 1","mn":"ADBE Vector Filter - Trim","hd":false}],"ip":133,"op":220,"st":4,"bm":0},{"ddd":0,"ind":4,"ty":4,"nm":"Capa de formas 33","sr":1,"ks":{"o":{"a":0,"k":100,"ix":11},"r":{"a":0,"k":62,"ix":10},"p":{"a":0,"k":[178,686,0],"ix":2},"a":{"a":0,"k":[257,271,0],"ix":1},"s":{"a":0,"k":[100,100,100],"ix":6}},"ao":0,"shapes":[{"ty":"gr","it":[{"ind":0,"ty":"sh","ix":1,"ks":{"a":0,"k":{"i":[[0,0],[34.404,31.652],[35.569,35.967],[42.643,32.385],[50.688,33.951],[39.992,25.316],[42.045,22.945],[98,-18]],"o":[[0,0],[-37.227,-34.248],[-37.652,-38.073],[-48.586,-36.898],[-39.325,-26.34],[-53.232,-33.697],[-71.219,-38.867],[-86,-28]],"v":[[245,255],[195,157],[70,94],[0,-28],[-142,-67],[-218,-183],[-360,-205],[-546,-362]],"c":false},"ix":2},"nm":"Trazado 1","mn":"ADBE Vector Shape - Group","hd":false},{"ty":"st","c":{"a":0,"k":[1,1,1,1],"ix":3},"o":{"a":0,"k":100,"ix":4},"w":{"a":0,"k":16,"ix":5},"lc":2,"lj":2,"bm":0,"nm":"Trazo 1","mn":"ADBE Vector Graphic - Stroke","hd":false},{"ty":"tr","p":{"a":0,"k":[0,0],"ix":2},"a":{"a":0,"k":[0,0],"ix":1},"s":{"a":0,"k":[104.858,106.226],"ix":3},"r":{"a":0,"k":0,"ix":6},"o":{"a":0,"k":100,"ix":7},"sk":{"a":0,"k":0,"ix":4},"sa":{"a":0,"k":0,"ix":5},"nm":"Transformar"}],"nm":"Forma 1","np":3,"cix":2,"bm":0,"ix":1,"mn":"ADBE Vector Group","hd":false},{"ty":"tm","s":{"a":1,"k":[{"i":{"x":[0.667],"y":[1]},"o":{"x":[0.167],"y":[0.167]},"t":131,"s":[0]},{"t":159,"s":[100]}],"ix":1},"e":{"a":1,"k":[{"i":{"x":[0.833],"y":[0.833]},"o":{"x":[0.167],"y":[0.167]},"t":131,"s":[0]},{"i":{"x":[0.667],"y":[1]},"o":{"x":[0.167],"y":[0.167]},"t":141,"s":[15]},{"t":159,"s":[100]}],"ix":2},"o":{"a":0,"k":0,"ix":3},"m":1,"ix":2,"nm":"Recortar trazados 1","mn":"ADBE Vector Filter - Trim","hd":false}],"ip":131,"op":218,"st":2,"bm":0},{"ddd":0,"ind":5,"ty":4,"nm":"Capa de formas 32","sr":1,"ks":{"o":{"a":0,"k":100,"ix":11},"r":{"a":0,"k":-180,"ix":10},"p":{"a":0,"k":[699,704,0],"ix":2},"a":{"a":0,"k":[257,271,0],"ix":1},"s":{"a":0,"k":[-100,-100,100],"ix":6}},"ao":0,"shapes":[{"ty":"gr","it":[{"ind":0,"ty":"sh","ix":1,"ks":{"a":0,"k":{"i":[[0,0],[34.404,31.652],[35.569,35.967],[42.643,32.385],[50.688,33.951],[39.992,25.316],[42.045,22.945],[98,-18]],"o":[[0,0],[-37.227,-34.248],[-37.652,-38.073],[-48.586,-36.898],[-39.325,-26.34],[-53.232,-33.697],[-71.219,-38.867],[-86,-28]],"v":[[245,255],[195,157],[70,94],[0,-28],[-142,-67],[-218,-183],[-360,-205],[-546,-362]],"c":false},"ix":2},"nm":"Trazado 1","mn":"ADBE Vector Shape - Group","hd":false},{"ty":"st","c":{"a":0,"k":[1,1,1,1],"ix":3},"o":{"a":0,"k":100,"ix":4},"w":{"a":0,"k":16,"ix":5},"lc":2,"lj":2,"bm":0,"nm":"Trazo 1","mn":"ADBE Vector Graphic - Stroke","hd":false},{"ty":"tr","p":{"a":0,"k":[0,0],"ix":2},"a":{"a":0,"k":[0,0],"ix":1},"s":{"a":0,"k":[104.858,106.226],"ix":3},"r":{"a":0,"k":0,"ix":6},"o":{"a":0,"k":100,"ix":7},"sk":{"a":0,"k":0,"ix":4},"sa":{"a":0,"k":0,"ix":5},"nm":"Transformar"}],"nm":"Forma 1","np":3,"cix":2,"bm":0,"ix":1,"mn":"ADBE Vector Group","hd":false},{"ty":"tm","s":{"a":1,"k":[{"i":{"x":[0.667],"y":[1]},"o":{"x":[0.167],"y":[0.167]},"t":137,"s":[0]},{"t":165,"s":[100]}],"ix":1},"e":{"a":1,"k":[{"i":{"x":[0.833],"y":[0.833]},"o":{"x":[0.167],"y":[0.167]},"t":137,"s":[0]},{"i":{"x":[0.667],"y":[1]},"o":{"x":[0.167],"y":[0.167]},"t":147,"s":[15]},{"t":165,"s":[100]}],"ix":2},"o":{"a":0,"k":0,"ix":3},"m":1,"ix":2,"nm":"Recortar trazados 1","mn":"ADBE Vector Filter - Trim","hd":false}],"ip":137,"op":224,"st":8,"bm":0},{"ddd":0,"ind":6,"ty":4,"nm":"Capa de formas 30","sr":1,"ks":{"o":{"a":0,"k":100,"ix":11},"r":{"a":0,"k":-20,"ix":10},"p":{"a":0,"k":[685,713,0],"ix":2},"a":{"a":0,"k":[257,271,0],"ix":1},"s":{"a":0,"k":[100,100,100],"ix":6}},"ao":0,"shapes":[{"ty":"gr","it":[{"ind":0,"ty":"sh","ix":1,"ks":{"a":0,"k":{"i":[[0,0],[34.404,31.652],[35.569,35.967],[42.643,32.385],[50.688,33.951],[39.992,25.316],[42.045,22.945],[98,-18]],"o":[[0,0],[-37.227,-34.248],[-37.652,-38.073],[-48.586,-36.898],[-39.325,-26.34],[-53.232,-33.697],[-71.219,-38.867],[-86,-28]],"v":[[245,255],[195,157],[70,94],[0,-28],[-142,-67],[-218,-183],[-360,-205],[-546,-362]],"c":false},"ix":2},"nm":"Trazado 1","mn":"ADBE Vector Shape - Group","hd":false},{"ty":"st","c":{"a":0,"k":[1,1,1,1],"ix":3},"o":{"a":0,"k":100,"ix":4},"w":{"a":0,"k":16,"ix":5},"lc":2,"lj":2,"bm":0,"nm":"Trazo 1","mn":"ADBE Vector Graphic - Stroke","hd":false},{"ty":"tr","p":{"a":0,"k":[0,0],"ix":2},"a":{"a":0,"k":[0,0],"ix":1},"s":{"a":0,"k":[104.858,106.226],"ix":3},"r":{"a":0,"k":0,"ix":6},"o":{"a":0,"k":100,"ix":7},"sk":{"a":0,"k":0,"ix":4},"sa":{"a":0,"k":0,"ix":5},"nm":"Transformar"}],"nm":"Forma 1","np":3,"cix":2,"bm":0,"ix":1,"mn":"ADBE Vector Group","hd":false},{"ty":"tm","s":{"a":1,"k":[{"i":{"x":[0.667],"y":[1]},"o":{"x":[0.167],"y":[0.167]},"t":131,"s":[0]},{"t":159,"s":[100]}],"ix":1},"e":{"a":1,"k":[{"i":{"x":[0.833],"y":[0.833]},"o":{"x":[0.167],"y":[0.167]},"t":131,"s":[0]},{"i":{"x":[0.667],"y":[1]},"o":{"x":[0.167],"y":[0.167]},"t":141,"s":[15]},{"t":159,"s":[100]}],"ix":2},"o":{"a":0,"k":0,"ix":3},"m":1,"ix":2,"nm":"Recortar trazados 1","mn":"ADBE Vector Filter - Trim","hd":false}],"ip":131,"op":218,"st":2,"bm":0},{"ddd":0,"ind":7,"ty":4,"nm":"Capa de formas 31","sr":1,"ks":{"o":{"a":0,"k":100,"ix":11},"r":{"a":0,"k":18,"ix":10},"p":{"a":0,"k":[682,721,0],"ix":2},"a":{"a":0,"k":[257,271,0],"ix":1},"s":{"a":0,"k":[100,100,100],"ix":6}},"ao":0,"shapes":[{"ty":"gr","it":[{"ind":0,"ty":"sh","ix":1,"ks":{"a":0,"k":{"i":[[0,0],[34.404,31.652],[35.569,35.967],[42.643,32.385],[50.688,33.951],[39.992,25.316],[42.045,22.945],[98,-18]],"o":[[0,0],[-37.227,-34.248],[-37.652,-38.073],[-48.586,-36.898],[-39.325,-26.34],[-53.232,-33.697],[-71.219,-38.867],[-86,-28]],"v":[[245,255],[195,157],[70,94],[0,-28],[-142,-67],[-218,-183],[-360,-205],[-546,-362]],"c":false},"ix":2},"nm":"Trazado 1","mn":"ADBE Vector Shape - Group","hd":false},{"ty":"st","c":{"a":0,"k":[1,1,1,1],"ix":3},"o":{"a":0,"k":100,"ix":4},"w":{"a":0,"k":16,"ix":5},"lc":2,"lj":2,"bm":0,"nm":"Trazo 1","mn":"ADBE Vector Graphic - Stroke","hd":false},{"ty":"tr","p":{"a":0,"k":[0,0],"ix":2},"a":{"a":0,"k":[0,0],"ix":1},"s":{"a":0,"k":[104.858,106.226],"ix":3},"r":{"a":0,"k":0,"ix":6},"o":{"a":0,"k":100,"ix":7},"sk":{"a":0,"k":0,"ix":4},"sa":{"a":0,"k":0,"ix":5},"nm":"Transformar"}],"nm":"Forma 1","np":3,"cix":2,"bm":0,"ix":1,"mn":"ADBE Vector Group","hd":false},{"ty":"tm","s":{"a":1,"k":[{"i":{"x":[0.667],"y":[1]},"o":{"x":[0.167],"y":[0.167]},"t":133,"s":[0]},{"t":161,"s":[100]}],"ix":1},"e":{"a":1,"k":[{"i":{"x":[0.833],"y":[0.833]},"o":{"x":[0.167],"y":[0.167]},"t":133,"s":[0]},{"i":{"x":[0.667],"y":[1]},"o":{"x":[0.167],"y":[0.167]},"t":143,"s":[15]},{"t":161,"s":[100]}],"ix":2},"o":{"a":0,"k":0,"ix":3},"m":1,"ix":2,"nm":"Recortar trazados 1","mn":"ADBE Vector Filter - Trim","hd":false}],"ip":133,"op":220,"st":4,"bm":0},{"ddd":0,"ind":8,"ty":4,"nm":"Capa de formas 29","sr":1,"ks":{"o":{"a":0,"k":100,"ix":11},"r":{"a":0,"k":-62,"ix":10},"p":{"a":0,"k":[722,686,0],"ix":2},"a":{"a":0,"k":[257,271,0],"ix":1},"s":{"a":0,"k":[-100,100,100],"ix":6}},"ao":0,"shapes":[{"ty":"gr","it":[{"ind":0,"ty":"sh","ix":1,"ks":{"a":0,"k":{"i":[[0,0],[34.404,31.652],[35.569,35.967],[42.643,32.385],[50.688,33.951],[39.992,25.316],[42.045,22.945],[98,-18]],"o":[[0,0],[-37.227,-34.248],[-37.652,-38.073],[-48.586,-36.898],[-39.325,-26.34],[-53.232,-33.697],[-71.219,-38.867],[-86,-28]],"v":[[245,255],[195,157],[70,94],[0,-28],[-142,-67],[-218,-183],[-360,-205],[-546,-362]],"c":false},"ix":2},"nm":"Trazado 1","mn":"ADBE Vector Shape - Group","hd":false},{"ty":"st","c":{"a":0,"k":[1,1,1,1],"ix":3},"o":{"a":0,"k":100,"ix":4},"w":{"a":0,"k":16,"ix":5},"lc":2,"lj":2,"bm":0,"nm":"Trazo 1","mn":"ADBE Vector Graphic - Stroke","hd":false},{"ty":"tr","p":{"a":0,"k":[0,0],"ix":2},"a":{"a":0,"k":[0,0],"ix":1},"s":{"a":0,"k":[104.858,106.226],"ix":3},"r":{"a":0,"k":0,"ix":6},"o":{"a":0,"k":100,"ix":7},"sk":{"a":0,"k":0,"ix":4},"sa":{"a":0,"k":0,"ix":5},"nm":"Transformar"}],"nm":"Forma 1","np":3,"cix":2,"bm":0,"ix":1,"mn":"ADBE Vector Group","hd":false},{"ty":"tm","s":{"a":1,"k":[{"i":{"x":[0.667],"y":[1]},"o":{"x":[0.167],"y":[0.167]},"t":135,"s":[0]},{"t":163,"s":[100]}],"ix":1},"e":{"a":1,"k":[{"i":{"x":[0.833],"y":[0.833]},"o":{"x":[0.167],"y":[0.167]},"t":135,"s":[0]},{"i":{"x":[0.667],"y":[1]},"o":{"x":[0.167],"y":[0.167]},"t":145,"s":[15]},{"t":163,"s":[100]}],"ix":2},"o":{"a":0,"k":0,"ix":3},"m":1,"ix":2,"nm":"Recortar trazados 1","mn":"ADBE Vector Filter - Trim","hd":false}],"ip":135,"op":222,"st":6,"bm":0},{"ddd":0,"ind":9,"ty":4,"nm":"Capa de formas 28","sr":1,"ks":{"o":{"a":0,"k":100,"ix":11},"r":{"a":1,"k":[{"i":{"x":[0.667],"y":[1]},"o":{"x":[0.333],"y":[0]},"t":129,"s":[136.534]},{"t":174.224609375,"s":[-73.484]}],"ix":10},"p":{"s":true,"x":{"a":1,"k":[{"i":{"x":[0.833],"y":[0.833]},"o":{"x":[0.167],"y":[0.167]},"t":128.692,"s":[702.925]},{"t":174.224609375,"s":[144.662]}],"ix":3},"y":{"a":1,"k":[{"i":{"x":[0.71],"y":[-1.462]},"o":{"x":[0.29],"y":[-1.423]},"t":129,"s":[682.78]},{"t":174.224609375,"s":[932.403]}],"ix":4}},"a":{"a":0,"k":[-15.375,-10.5,0],"ix":1},"s":{"a":0,"k":[-155,155,100],"ix":6}},"ao":0,"shapes":[{"ty":"gr","it":[{"ty":"rc","d":1,"s":{"a":0,"k":[11,11],"ix":2},"p":{"a":0,"k":[0,0],"ix":3},"r":{"a":0,"k":0,"ix":4},"nm":"Trazado de rectángulo 1","mn":"ADBE Vector Shape - Rect","hd":false},{"ty":"fl","c":{"a":0,"k":[1,1,1,1],"ix":4},"o":{"a":0,"k":100,"ix":5},"r":1,"bm":0,"nm":"Relleno 1","mn":"ADBE Vector Graphic - Fill","hd":false},{"ty":"tr","p":{"a":0,"k":[-15.5,-10.5],"ix":2},"a":{"a":0,"k":[0,0],"ix":1},"s":{"a":0,"k":[100,100],"ix":3},"r":{"a":0,"k":0,"ix":6},"o":{"a":0,"k":100,"ix":7},"sk":{"a":0,"k":0,"ix":4},"sa":{"a":0,"k":0,"ix":5},"nm":"Transformar"}],"nm":"Rectángulo 1","np":3,"cix":2,"bm":0,"ix":1,"mn":"ADBE Vector Group","hd":false}],"ip":129,"op":216,"st":0,"bm":0},{"ddd":0,"ind":10,"ty":4,"nm":"Capa de formas 27","sr":1,"ks":{"o":{"a":0,"k":100,"ix":11},"r":{"a":1,"k":[{"i":{"x":[0.667],"y":[1]},"o":{"x":[0.333],"y":[0]},"t":129,"s":[0]},{"t":179,"s":[-213]}],"ix":10},"p":{"s":true,"x":{"a":1,"k":[{"i":{"x":[0.833],"y":[0.833]},"o":{"x":[0.167],"y":[0.167]},"t":128.692,"s":[702.925]},{"t":179,"s":[-21.01]}],"ix":3},"y":{"a":1,"k":[{"i":{"x":[0.556],"y":[-3.453]},"o":{"x":[0.128],"y":[-2.506]},"t":129,"s":[682.78]},{"t":179,"s":[818.28]}],"ix":4}},"a":{"a":0,"k":[-15.375,-10.5,0],"ix":1},"s":{"a":0,"k":[-155,155,100],"ix":6}},"ao":0,"shapes":[{"ty":"gr","it":[{"ty":"rc","d":1,"s":{"a":0,"k":[11,11],"ix":2},"p":{"a":0,"k":[0,0],"ix":3},"r":{"a":0,"k":0,"ix":4},"nm":"Trazado de rectángulo 1","mn":"ADBE Vector Shape - Rect","hd":false},{"ty":"fl","c":{"a":0,"k":[1,1,1,1],"ix":4},"o":{"a":0,"k":100,"ix":5},"r":1,"bm":0,"nm":"Relleno 1","mn":"ADBE Vector Graphic - Fill","hd":false},{"ty":"tr","p":{"a":0,"k":[-15.5,-10.5],"ix":2},"a":{"a":0,"k":[0,0],"ix":1},"s":{"a":0,"k":[100,100],"ix":3},"r":{"a":0,"k":0,"ix":6},"o":{"a":0,"k":100,"ix":7},"sk":{"a":0,"k":0,"ix":4},"sa":{"a":0,"k":0,"ix":5},"nm":"Transformar"}],"nm":"Rectángulo 1","np":3,"cix":2,"bm":0,"ix":1,"mn":"ADBE Vector Group","hd":false}],"ip":129,"op":216,"st":0,"bm":0},{"ddd":0,"ind":11,"ty":4,"nm":"Capa de formas 26","sr":1,"ks":{"o":{"a":0,"k":100,"ix":11},"r":{"a":1,"k":[{"i":{"x":[0.667],"y":[1]},"o":{"x":[0.333],"y":[0]},"t":129,"s":[-298.478]},{"t":179,"s":[-511.478]}],"ix":10},"p":{"s":true,"x":{"a":1,"k":[{"i":{"x":[0.833],"y":[0.833]},"o":{"x":[0.167],"y":[0.167]},"t":128.692,"s":[702.925]},{"t":179,"s":[-21.01]}],"ix":3},"y":{"a":1,"k":[{"i":{"x":[0.443],"y":[-1.415]},"o":{"x":[0.338],"y":[-1.991]},"t":129,"s":[682.78]},{"t":179,"s":[965.25]}],"ix":4}},"a":{"a":0,"k":[-15.375,-10.5,0],"ix":1},"s":{"a":0,"k":[-155,155,100],"ix":6}},"ao":0,"shapes":[{"ty":"gr","it":[{"ty":"rc","d":1,"s":{"a":0,"k":[11,11],"ix":2},"p":{"a":0,"k":[0,0],"ix":3},"r":{"a":0,"k":0,"ix":4},"nm":"Trazado de rectángulo 1","mn":"ADBE Vector Shape - Rect","hd":false},{"ty":"fl","c":{"a":0,"k":[1,1,1,1],"ix":4},"o":{"a":0,"k":100,"ix":5},"r":1,"bm":0,"nm":"Relleno 1","mn":"ADBE Vector Graphic - Fill","hd":false},{"ty":"tr","p":{"a":0,"k":[-15.5,-10.5],"ix":2},"a":{"a":0,"k":[0,0],"ix":1},"s":{"a":0,"k":[100,100],"ix":3},"r":{"a":0,"k":0,"ix":6},"o":{"a":0,"k":100,"ix":7},"sk":{"a":0,"k":0,"ix":4},"sa":{"a":0,"k":0,"ix":5},"nm":"Transformar"}],"nm":"Rectángulo 1","np":3,"cix":2,"bm":0,"ix":1,"mn":"ADBE Vector Group","hd":false}],"ip":129,"op":216,"st":0,"bm":0},{"ddd":0,"ind":12,"ty":4,"nm":"Capa de formas 25","sr":1,"ks":{"o":{"a":0,"k":100,"ix":11},"r":{"a":1,"k":[{"i":{"x":[0.667],"y":[1]},"o":{"x":[0.333],"y":[0]},"t":129,"s":[-525.218]},{"t":179,"s":[-738.218]}],"ix":10},"p":{"s":true,"x":{"a":1,"k":[{"i":{"x":[0.833],"y":[0.833]},"o":{"x":[0.167],"y":[0.167]},"t":128.692,"s":[702.925]},{"t":179,"s":[32.24]}],"ix":3},"y":{"a":1,"k":[{"i":{"x":[0.525],"y":[-0.895]},"o":{"x":[0.235],"y":[-1.213]},"t":129,"s":[682.78]},{"t":179,"s":[1040.554]}],"ix":4}},"a":{"a":0,"k":[-15.375,-10.5,0],"ix":1},"s":{"a":0,"k":[-155,155,100],"ix":6}},"ao":0,"shapes":[{"ty":"gr","it":[{"ty":"rc","d":1,"s":{"a":0,"k":[11,11],"ix":2},"p":{"a":0,"k":[0,0],"ix":3},"r":{"a":0,"k":0,"ix":4},"nm":"Trazado de rectángulo 1","mn":"ADBE Vector Shape - Rect","hd":false},{"ty":"fl","c":{"a":0,"k":[1,1,1,1],"ix":4},"o":{"a":0,"k":100,"ix":5},"r":1,"bm":0,"nm":"Relleno 1","mn":"ADBE Vector Graphic - Fill","hd":false},{"ty":"tr","p":{"a":0,"k":[-15.5,-10.5],"ix":2},"a":{"a":0,"k":[0,0],"ix":1},"s":{"a":0,"k":[100,100],"ix":3},"r":{"a":0,"k":0,"ix":6},"o":{"a":0,"k":100,"ix":7},"sk":{"a":0,"k":0,"ix":4},"sa":{"a":0,"k":0,"ix":5},"nm":"Transformar"}],"nm":"Rectángulo 1","np":3,"cix":2,"bm":0,"ix":1,"mn":"ADBE Vector Group","hd":false}],"ip":129,"op":216,"st":0,"bm":0},{"ddd":0,"ind":13,"ty":4,"nm":"Capa de formas 24","sr":1,"ks":{"o":{"a":0,"k":100,"ix":11},"r":{"a":1,"k":[{"i":{"x":[0.667],"y":[1]},"o":{"x":[0.333],"y":[0]},"t":129,"s":[0]},{"t":179,"s":[-213]}],"ix":10},"p":{"s":true,"x":{"a":1,"k":[{"i":{"x":[0.833],"y":[0.833]},"o":{"x":[0.167],"y":[0.167]},"t":128.692,"s":[702.925]},{"t":179,"s":[94.573]}],"ix":3},"y":{"a":1,"k":[{"i":{"x":[0.525],"y":[-4.004]},"o":{"x":[0.29],"y":[-2.899]},"t":129,"s":[682.78]},{"t":179,"s":[818.28]}],"ix":4}},"a":{"a":0,"k":[-15.375,-10.5,0],"ix":1},"s":{"a":0,"k":[-155,155,100],"ix":6}},"ao":0,"shapes":[{"ty":"gr","it":[{"ty":"rc","d":1,"s":{"a":0,"k":[11,11],"ix":2},"p":{"a":0,"k":[0,0],"ix":3},"r":{"a":0,"k":0,"ix":4},"nm":"Trazado de rectángulo 1","mn":"ADBE Vector Shape - Rect","hd":false},{"ty":"fl","c":{"a":0,"k":[1,1,1,1],"ix":4},"o":{"a":0,"k":100,"ix":5},"r":1,"bm":0,"nm":"Relleno 1","mn":"ADBE Vector Graphic - Fill","hd":false},{"ty":"tr","p":{"a":0,"k":[-15.5,-10.5],"ix":2},"a":{"a":0,"k":[0,0],"ix":1},"s":{"a":0,"k":[100,100],"ix":3},"r":{"a":0,"k":0,"ix":6},"o":{"a":0,"k":100,"ix":7},"sk":{"a":0,"k":0,"ix":4},"sa":{"a":0,"k":0,"ix":5},"nm":"Transformar"}],"nm":"Rectángulo 1","np":3,"cix":2,"bm":0,"ix":1,"mn":"ADBE Vector Group","hd":false}],"ip":129,"op":216,"st":0,"bm":0},{"ddd":0,"ind":14,"ty":4,"nm":"Capa de formas 23","sr":1,"ks":{"o":{"a":0,"k":100,"ix":11},"r":{"a":1,"k":[{"i":{"x":[0.667],"y":[1]},"o":{"x":[0.333],"y":[0]},"t":129,"s":[0]},{"t":184.3916015625,"s":[-210.438]}],"ix":10},"p":{"s":true,"x":{"a":1,"k":[{"i":{"x":[0.833],"y":[0.833]},"o":{"x":[0.167],"y":[0.167]},"t":128.692,"s":[702.925]},{"t":184.3916015625,"s":[-18.447]}],"ix":3},"y":{"a":1,"k":[{"i":{"x":[0.525],"y":[-4.65]},"o":{"x":[0.337],"y":[-2.229]},"t":129,"s":[682.78]},{"t":184.3916015625,"s":[815.718]}],"ix":4}},"a":{"a":0,"k":[-15.375,-10.5,0],"ix":1},"s":{"a":0,"k":[-155,155,100],"ix":6}},"ao":0,"shapes":[{"ty":"gr","it":[{"ty":"rc","d":1,"s":{"a":0,"k":[11,11],"ix":2},"p":{"a":0,"k":[0,0],"ix":3},"r":{"a":0,"k":0,"ix":4},"nm":"Trazado de rectángulo 1","mn":"ADBE Vector Shape - Rect","hd":false},{"ty":"fl","c":{"a":0,"k":[1,1,1,1],"ix":4},"o":{"a":0,"k":100,"ix":5},"r":1,"bm":0,"nm":"Relleno 1","mn":"ADBE Vector Graphic - Fill","hd":false},{"ty":"tr","p":{"a":0,"k":[-15.5,-10.5],"ix":2},"a":{"a":0,"k":[0,0],"ix":1},"s":{"a":0,"k":[100,100],"ix":3},"r":{"a":0,"k":0,"ix":6},"o":{"a":0,"k":100,"ix":7},"sk":{"a":0,"k":0,"ix":4},"sa":{"a":0,"k":0,"ix":5},"nm":"Transformar"}],"nm":"Rectángulo 1","np":3,"cix":2,"bm":0,"ix":1,"mn":"ADBE Vector Group","hd":false}],"ip":129,"op":216,"st":0,"bm":0},{"ddd":0,"ind":15,"ty":4,"nm":"Capa de formas 22","sr":1,"ks":{"o":{"a":0,"k":100,"ix":11},"r":{"a":1,"k":[{"i":{"x":[0.667],"y":[1]},"o":{"x":[0.333],"y":[0]},"t":129,"s":[-125.826]},{"t":179,"s":[-338.826]}],"ix":10},"p":{"s":true,"x":{"a":1,"k":[{"i":{"x":[0.833],"y":[0.833]},"o":{"x":[0.167],"y":[0.167]},"t":128.692,"s":[702.925]},{"t":179,"s":[29.827]}],"ix":3},"y":{"a":1,"k":[{"i":{"x":[0.525],"y":[-1.612]},"o":{"x":[0.005],"y":[-0.285]},"t":129,"s":[682.78]},{"t":179,"s":[942.337]}],"ix":4}},"a":{"a":0,"k":[-15.375,-10.5,0],"ix":1},"s":{"a":0,"k":[-155,155,100],"ix":6}},"ao":0,"shapes":[{"ty":"gr","it":[{"ty":"rc","d":1,"s":{"a":0,"k":[11,11],"ix":2},"p":{"a":0,"k":[0,0],"ix":3},"r":{"a":0,"k":0,"ix":4},"nm":"Trazado de rectángulo 1","mn":"ADBE Vector Shape - Rect","hd":false},{"ty":"fl","c":{"a":0,"k":[1,1,1,1],"ix":4},"o":{"a":0,"k":100,"ix":5},"r":1,"bm":0,"nm":"Relleno 1","mn":"ADBE Vector Graphic - Fill","hd":false},{"ty":"tr","p":{"a":0,"k":[-15.5,-10.5],"ix":2},"a":{"a":0,"k":[0,0],"ix":1},"s":{"a":0,"k":[100,100],"ix":3},"r":{"a":0,"k":0,"ix":6},"o":{"a":0,"k":100,"ix":7},"sk":{"a":0,"k":0,"ix":4},"sa":{"a":0,"k":0,"ix":5},"nm":"Transformar"}],"nm":"Rectángulo 1","np":3,"cix":2,"bm":0,"ix":1,"mn":"ADBE Vector Group","hd":false}],"ip":129,"op":216,"st":0,"bm":0},{"ddd":0,"ind":16,"ty":4,"nm":"Capa de formas 21","sr":1,"ks":{"o":{"a":0,"k":100,"ix":11},"r":{"a":1,"k":[{"i":{"x":[0.667],"y":[1]},"o":{"x":[0.333],"y":[0]},"t":129,"s":[136.534]},{"t":179,"s":[-76.466]}],"ix":10},"p":{"s":true,"x":{"a":1,"k":[{"i":{"x":[0.833],"y":[0.833]},"o":{"x":[0.167],"y":[0.167]},"t":128.692,"s":[702.925]},{"t":179,"s":[141.68]}],"ix":3},"y":{"a":1,"k":[{"i":{"x":[0.71],"y":[-1.69]},"o":{"x":[0.29],"y":[-1.555]},"t":129,"s":[682.78]},{"t":179,"s":[935.384]}],"ix":4}},"a":{"a":0,"k":[-15.375,-10.5,0],"ix":1},"s":{"a":0,"k":[-155,155,100],"ix":6}},"ao":0,"shapes":[{"ty":"gr","it":[{"ty":"rc","d":1,"s":{"a":0,"k":[11,11],"ix":2},"p":{"a":0,"k":[0,0],"ix":3},"r":{"a":0,"k":0,"ix":4},"nm":"Trazado de rectángulo 1","mn":"ADBE Vector Shape - Rect","hd":false},{"ty":"fl","c":{"a":0,"k":[1,1,1,1],"ix":4},"o":{"a":0,"k":100,"ix":5},"r":1,"bm":0,"nm":"Relleno 1","mn":"ADBE Vector Graphic - Fill","hd":false},{"ty":"tr","p":{"a":0,"k":[-15.5,-10.5],"ix":2},"a":{"a":0,"k":[0,0],"ix":1},"s":{"a":0,"k":[100,100],"ix":3},"r":{"a":0,"k":0,"ix":6},"o":{"a":0,"k":100,"ix":7},"sk":{"a":0,"k":0,"ix":4},"sa":{"a":0,"k":0,"ix":5},"nm":"Transformar"}],"nm":"Rectángulo 1","np":3,"cix":2,"bm":0,"ix":1,"mn":"ADBE Vector Group","hd":false}],"ip":129,"op":216,"st":0,"bm":0},{"ddd":0,"ind":17,"ty":4,"nm":"Capa de formas 20","sr":1,"ks":{"o":{"a":0,"k":100,"ix":11},"r":{"a":1,"k":[{"i":{"x":[0.667],"y":[1]},"o":{"x":[0.333],"y":[0]},"t":129,"s":[0]},{"t":179,"s":[-213]}],"ix":10},"p":{"s":true,"x":{"a":1,"k":[{"i":{"x":[0.833],"y":[0.833]},"o":{"x":[0.167],"y":[0.167]},"t":128.692,"s":[702.925]},{"t":179,"s":[-21.01]}],"ix":3},"y":{"a":1,"k":[{"i":{"x":[0.371],"y":[-2.227]},"o":{"x":[0.273],"y":[-1.508]},"t":129,"s":[682.78]},{"t":179,"s":[818.28]}],"ix":4}},"a":{"a":0,"k":[-15.375,-10.5,0],"ix":1},"s":{"a":0,"k":[-155,155,100],"ix":6}},"ao":0,"shapes":[{"ty":"gr","it":[{"ty":"rc","d":1,"s":{"a":0,"k":[11,11],"ix":2},"p":{"a":0,"k":[0,0],"ix":3},"r":{"a":0,"k":0,"ix":4},"nm":"Trazado de rectángulo 1","mn":"ADBE Vector Shape - Rect","hd":false},{"ty":"fl","c":{"a":0,"k":[1,1,1,1],"ix":4},"o":{"a":0,"k":100,"ix":5},"r":1,"bm":0,"nm":"Relleno 1","mn":"ADBE Vector Graphic - Fill","hd":false},{"ty":"tr","p":{"a":0,"k":[-15.5,-10.5],"ix":2},"a":{"a":0,"k":[0,0],"ix":1},"s":{"a":0,"k":[100,100],"ix":3},"r":{"a":0,"k":0,"ix":6},"o":{"a":0,"k":100,"ix":7},"sk":{"a":0,"k":0,"ix":4},"sa":{"a":0,"k":0,"ix":5},"nm":"Transformar"}],"nm":"Rectángulo 1","np":3,"cix":2,"bm":0,"ix":1,"mn":"ADBE Vector Group","hd":false}],"ip":129,"op":216,"st":0,"bm":0},{"ddd":0,"ind":18,"ty":4,"nm":"Capa de formas 19","sr":1,"ks":{"o":{"a":0,"k":100,"ix":11},"r":{"a":1,"k":[{"i":{"x":[0.667],"y":[1]},"o":{"x":[0.333],"y":[0]},"t":129,"s":[-298.478]},{"t":179,"s":[-511.478]}],"ix":10},"p":{"s":true,"x":{"a":1,"k":[{"i":{"x":[0.833],"y":[0.833]},"o":{"x":[0.167],"y":[0.167]},"t":128.692,"s":[702.925]},{"t":179,"s":[-52.01]}],"ix":3},"y":{"a":1,"k":[{"i":{"x":[0.509],"y":[2.405]},"o":{"x":[0.044],"y":[0.375]},"t":129,"s":[682.78]},{"t":179,"s":[479.28]}],"ix":4}},"a":{"a":0,"k":[-15.375,-10.5,0],"ix":1},"s":{"a":0,"k":[-155,155,100],"ix":6}},"ao":0,"shapes":[{"ty":"gr","it":[{"ty":"rc","d":1,"s":{"a":0,"k":[11,11],"ix":2},"p":{"a":0,"k":[0,0],"ix":3},"r":{"a":0,"k":0,"ix":4},"nm":"Trazado de rectángulo 1","mn":"ADBE Vector Shape - Rect","hd":false},{"ty":"fl","c":{"a":0,"k":[1,1,1,1],"ix":4},"o":{"a":0,"k":100,"ix":5},"r":1,"bm":0,"nm":"Relleno 1","mn":"ADBE Vector Graphic - Fill","hd":false},{"ty":"tr","p":{"a":0,"k":[-15.5,-10.5],"ix":2},"a":{"a":0,"k":[0,0],"ix":1},"s":{"a":0,"k":[100,100],"ix":3},"r":{"a":0,"k":0,"ix":6},"o":{"a":0,"k":100,"ix":7},"sk":{"a":0,"k":0,"ix":4},"sa":{"a":0,"k":0,"ix":5},"nm":"Transformar"}],"nm":"Rectángulo 1","np":3,"cix":2,"bm":0,"ix":1,"mn":"ADBE Vector Group","hd":false}],"ip":129,"op":216,"st":0,"bm":0},{"ddd":0,"ind":19,"ty":4,"nm":"Capa de formas 18","sr":1,"ks":{"o":{"a":0,"k":100,"ix":11},"r":{"a":1,"k":[{"i":{"x":[0.667],"y":[1]},"o":{"x":[0.333],"y":[0]},"t":129,"s":[-525.218]},{"t":178.5380859375,"s":[-738.218]}],"ix":10},"p":{"s":true,"x":{"a":1,"k":[{"i":{"x":[0.833],"y":[0.833]},"o":{"x":[0.167],"y":[0.167]},"t":128.692,"s":[702.925]},{"t":178.5380859375,"s":[-21.01]}],"ix":3},"y":{"a":1,"k":[{"i":{"x":[0.525],"y":[-3.958]},"o":{"x":[0.29],"y":[-2.872]},"t":129,"s":[682.78]},{"t":178.5380859375,"s":[818.28]}],"ix":4}},"a":{"a":0,"k":[-15.375,-10.5,0],"ix":1},"s":{"a":0,"k":[-155,155,100],"ix":6}},"ao":0,"shapes":[{"ty":"gr","it":[{"ty":"rc","d":1,"s":{"a":0,"k":[11,11],"ix":2},"p":{"a":0,"k":[0,0],"ix":3},"r":{"a":0,"k":0,"ix":4},"nm":"Trazado de rectángulo 1","mn":"ADBE Vector Shape - Rect","hd":false},{"ty":"fl","c":{"a":0,"k":[1,1,1,1],"ix":4},"o":{"a":0,"k":100,"ix":5},"r":1,"bm":0,"nm":"Relleno 1","mn":"ADBE Vector Graphic - Fill","hd":false},{"ty":"tr","p":{"a":0,"k":[-15.5,-10.5],"ix":2},"a":{"a":0,"k":[0,0],"ix":1},"s":{"a":0,"k":[100,100],"ix":3},"r":{"a":0,"k":0,"ix":6},"o":{"a":0,"k":100,"ix":7},"sk":{"a":0,"k":0,"ix":4},"sa":{"a":0,"k":0,"ix":5},"nm":"Transformar"}],"nm":"Rectángulo 1","np":3,"cix":2,"bm":0,"ix":1,"mn":"ADBE Vector Group","hd":false}],"ip":129,"op":216,"st":0,"bm":0},{"ddd":0,"ind":20,"ty":4,"nm":"Capa de formas 17","sr":1,"ks":{"o":{"a":0,"k":100,"ix":11},"r":{"a":1,"k":[{"i":{"x":[0.667],"y":[1]},"o":{"x":[0.333],"y":[0]},"t":129,"s":[-136.534]},{"t":174.224609375,"s":[73.484]}],"ix":10},"p":{"s":true,"x":{"a":1,"k":[{"i":{"x":[0.833],"y":[0.833]},"o":{"x":[0.167],"y":[0.167]},"t":128.692,"s":[197.075]},{"t":174.224609375,"s":[755.338]}],"ix":3},"y":{"a":1,"k":[{"i":{"x":[0.71],"y":[-1.462]},"o":{"x":[0.29],"y":[-1.423]},"t":129,"s":[682.78]},{"t":174.224609375,"s":[932.403]}],"ix":4}},"a":{"a":0,"k":[-15.375,-10.5,0],"ix":1},"s":{"a":0,"k":[155,155,100],"ix":6}},"ao":0,"shapes":[{"ty":"gr","it":[{"ty":"rc","d":1,"s":{"a":0,"k":[11,11],"ix":2},"p":{"a":0,"k":[0,0],"ix":3},"r":{"a":0,"k":0,"ix":4},"nm":"Trazado de rectángulo 1","mn":"ADBE Vector Shape - Rect","hd":false},{"ty":"fl","c":{"a":0,"k":[1,1,1,1],"ix":4},"o":{"a":0,"k":100,"ix":5},"r":1,"bm":0,"nm":"Relleno 1","mn":"ADBE Vector Graphic - Fill","hd":false},{"ty":"tr","p":{"a":0,"k":[-15.5,-10.5],"ix":2},"a":{"a":0,"k":[0,0],"ix":1},"s":{"a":0,"k":[100,100],"ix":3},"r":{"a":0,"k":0,"ix":6},"o":{"a":0,"k":100,"ix":7},"sk":{"a":0,"k":0,"ix":4},"sa":{"a":0,"k":0,"ix":5},"nm":"Transformar"}],"nm":"Rectángulo 1","np":3,"cix":2,"bm":0,"ix":1,"mn":"ADBE Vector Group","hd":false}],"ip":129,"op":216,"st":0,"bm":0},{"ddd":0,"ind":21,"ty":4,"nm":"Capa de formas 16","sr":1,"ks":{"o":{"a":0,"k":100,"ix":11},"r":{"a":1,"k":[{"i":{"x":[0.667],"y":[1]},"o":{"x":[0.333],"y":[0]},"t":129,"s":[0]},{"t":179,"s":[213]}],"ix":10},"p":{"s":true,"x":{"a":1,"k":[{"i":{"x":[0.833],"y":[0.833]},"o":{"x":[0.167],"y":[0.167]},"t":128.692,"s":[197.075]},{"t":179,"s":[921.01]}],"ix":3},"y":{"a":1,"k":[{"i":{"x":[0.556],"y":[-3.453]},"o":{"x":[0.128],"y":[-2.506]},"t":129,"s":[682.78]},{"t":179,"s":[818.28]}],"ix":4}},"a":{"a":0,"k":[-15.375,-10.5,0],"ix":1},"s":{"a":0,"k":[155,155,100],"ix":6}},"ao":0,"shapes":[{"ty":"gr","it":[{"ty":"rc","d":1,"s":{"a":0,"k":[11,11],"ix":2},"p":{"a":0,"k":[0,0],"ix":3},"r":{"a":0,"k":0,"ix":4},"nm":"Trazado de rectángulo 1","mn":"ADBE Vector Shape - Rect","hd":false},{"ty":"fl","c":{"a":0,"k":[1,1,1,1],"ix":4},"o":{"a":0,"k":100,"ix":5},"r":1,"bm":0,"nm":"Relleno 1","mn":"ADBE Vector Graphic - Fill","hd":false},{"ty":"tr","p":{"a":0,"k":[-15.5,-10.5],"ix":2},"a":{"a":0,"k":[0,0],"ix":1},"s":{"a":0,"k":[100,100],"ix":3},"r":{"a":0,"k":0,"ix":6},"o":{"a":0,"k":100,"ix":7},"sk":{"a":0,"k":0,"ix":4},"sa":{"a":0,"k":0,"ix":5},"nm":"Transformar"}],"nm":"Rectángulo 1","np":3,"cix":2,"bm":0,"ix":1,"mn":"ADBE Vector Group","hd":false}],"ip":129,"op":216,"st":0,"bm":0},{"ddd":0,"ind":22,"ty":4,"nm":"Capa de formas 15","sr":1,"ks":{"o":{"a":0,"k":100,"ix":11},"r":{"a":1,"k":[{"i":{"x":[0.667],"y":[1]},"o":{"x":[0.333],"y":[0]},"t":129,"s":[298.478]},{"t":179,"s":[511.478]}],"ix":10},"p":{"s":true,"x":{"a":1,"k":[{"i":{"x":[0.833],"y":[0.833]},"o":{"x":[0.167],"y":[0.167]},"t":128.692,"s":[197.075]},{"t":179,"s":[921.01]}],"ix":3},"y":{"a":1,"k":[{"i":{"x":[0.443],"y":[-1.415]},"o":{"x":[0.338],"y":[-1.991]},"t":129,"s":[682.78]},{"t":179,"s":[965.25]}],"ix":4}},"a":{"a":0,"k":[-15.375,-10.5,0],"ix":1},"s":{"a":0,"k":[155,155,100],"ix":6}},"ao":0,"shapes":[{"ty":"gr","it":[{"ty":"rc","d":1,"s":{"a":0,"k":[11,11],"ix":2},"p":{"a":0,"k":[0,0],"ix":3},"r":{"a":0,"k":0,"ix":4},"nm":"Trazado de rectángulo 1","mn":"ADBE Vector Shape - Rect","hd":false},{"ty":"fl","c":{"a":0,"k":[1,1,1,1],"ix":4},"o":{"a":0,"k":100,"ix":5},"r":1,"bm":0,"nm":"Relleno 1","mn":"ADBE Vector Graphic - Fill","hd":false},{"ty":"tr","p":{"a":0,"k":[-15.5,-10.5],"ix":2},"a":{"a":0,"k":[0,0],"ix":1},"s":{"a":0,"k":[100,100],"ix":3},"r":{"a":0,"k":0,"ix":6},"o":{"a":0,"k":100,"ix":7},"sk":{"a":0,"k":0,"ix":4},"sa":{"a":0,"k":0,"ix":5},"nm":"Transformar"}],"nm":"Rectángulo 1","np":3,"cix":2,"bm":0,"ix":1,"mn":"ADBE Vector Group","hd":false}],"ip":129,"op":216,"st":0,"bm":0},{"ddd":0,"ind":23,"ty":4,"nm":"Capa de formas 14","sr":1,"ks":{"o":{"a":0,"k":100,"ix":11},"r":{"a":1,"k":[{"i":{"x":[0.667],"y":[1]},"o":{"x":[0.333],"y":[0]},"t":129,"s":[525.218]},{"t":179,"s":[738.218]}],"ix":10},"p":{"s":true,"x":{"a":1,"k":[{"i":{"x":[0.833],"y":[0.833]},"o":{"x":[0.167],"y":[0.167]},"t":128.692,"s":[197.075]},{"t":179,"s":[867.76]}],"ix":3},"y":{"a":1,"k":[{"i":{"x":[0.525],"y":[-0.895]},"o":{"x":[0.235],"y":[-1.213]},"t":129,"s":[682.78]},{"t":179,"s":[1040.554]}],"ix":4}},"a":{"a":0,"k":[-15.375,-10.5,0],"ix":1},"s":{"a":0,"k":[155,155,100],"ix":6}},"ao":0,"shapes":[{"ty":"gr","it":[{"ty":"rc","d":1,"s":{"a":0,"k":[11,11],"ix":2},"p":{"a":0,"k":[0,0],"ix":3},"r":{"a":0,"k":0,"ix":4},"nm":"Trazado de rectángulo 1","mn":"ADBE Vector Shape - Rect","hd":false},{"ty":"fl","c":{"a":0,"k":[1,1,1,1],"ix":4},"o":{"a":0,"k":100,"ix":5},"r":1,"bm":0,"nm":"Relleno 1","mn":"ADBE Vector Graphic - Fill","hd":false},{"ty":"tr","p":{"a":0,"k":[-15.5,-10.5],"ix":2},"a":{"a":0,"k":[0,0],"ix":1},"s":{"a":0,"k":[100,100],"ix":3},"r":{"a":0,"k":0,"ix":6},"o":{"a":0,"k":100,"ix":7},"sk":{"a":0,"k":0,"ix":4},"sa":{"a":0,"k":0,"ix":5},"nm":"Transformar"}],"nm":"Rectángulo 1","np":3,"cix":2,"bm":0,"ix":1,"mn":"ADBE Vector Group","hd":false}],"ip":129,"op":216,"st":0,"bm":0},{"ddd":0,"ind":24,"ty":4,"nm":"Capa de formas 13","sr":1,"ks":{"o":{"a":0,"k":100,"ix":11},"r":{"a":1,"k":[{"i":{"x":[0.667],"y":[1]},"o":{"x":[0.333],"y":[0]},"t":129,"s":[0]},{"t":179,"s":[213]}],"ix":10},"p":{"s":true,"x":{"a":1,"k":[{"i":{"x":[0.833],"y":[0.833]},"o":{"x":[0.167],"y":[0.167]},"t":128.692,"s":[197.075]},{"t":179,"s":[805.427]}],"ix":3},"y":{"a":1,"k":[{"i":{"x":[0.525],"y":[-4.004]},"o":{"x":[0.29],"y":[-2.899]},"t":129,"s":[682.78]},{"t":179,"s":[818.28]}],"ix":4}},"a":{"a":0,"k":[-15.375,-10.5,0],"ix":1},"s":{"a":0,"k":[155,155,100],"ix":6}},"ao":0,"shapes":[{"ty":"gr","it":[{"ty":"rc","d":1,"s":{"a":0,"k":[11,11],"ix":2},"p":{"a":0,"k":[0,0],"ix":3},"r":{"a":0,"k":0,"ix":4},"nm":"Trazado de rectángulo 1","mn":"ADBE Vector Shape - Rect","hd":false},{"ty":"fl","c":{"a":0,"k":[1,1,1,1],"ix":4},"o":{"a":0,"k":100,"ix":5},"r":1,"bm":0,"nm":"Relleno 1","mn":"ADBE Vector Graphic - Fill","hd":false},{"ty":"tr","p":{"a":0,"k":[-15.5,-10.5],"ix":2},"a":{"a":0,"k":[0,0],"ix":1},"s":{"a":0,"k":[100,100],"ix":3},"r":{"a":0,"k":0,"ix":6},"o":{"a":0,"k":100,"ix":7},"sk":{"a":0,"k":0,"ix":4},"sa":{"a":0,"k":0,"ix":5},"nm":"Transformar"}],"nm":"Rectángulo 1","np":3,"cix":2,"bm":0,"ix":1,"mn":"ADBE Vector Group","hd":false}],"ip":129,"op":216,"st":0,"bm":0},{"ddd":0,"ind":25,"ty":4,"nm":"Capa de formas 12","sr":1,"ks":{"o":{"a":0,"k":100,"ix":11},"r":{"a":1,"k":[{"i":{"x":[0.667],"y":[1]},"o":{"x":[0.333],"y":[0]},"t":129,"s":[0]},{"t":184.3916015625,"s":[210.438]}],"ix":10},"p":{"s":true,"x":{"a":1,"k":[{"i":{"x":[0.833],"y":[0.833]},"o":{"x":[0.167],"y":[0.167]},"t":128.692,"s":[197.075]},{"t":184.3916015625,"s":[918.447]}],"ix":3},"y":{"a":1,"k":[{"i":{"x":[0.525],"y":[-4.65]},"o":{"x":[0.337],"y":[-2.229]},"t":129,"s":[682.78]},{"t":184.3916015625,"s":[815.718]}],"ix":4}},"a":{"a":0,"k":[-15.375,-10.5,0],"ix":1},"s":{"a":0,"k":[155,155,100],"ix":6}},"ao":0,"shapes":[{"ty":"gr","it":[{"ty":"rc","d":1,"s":{"a":0,"k":[11,11],"ix":2},"p":{"a":0,"k":[0,0],"ix":3},"r":{"a":0,"k":0,"ix":4},"nm":"Trazado de rectángulo 1","mn":"ADBE Vector Shape - Rect","hd":false},{"ty":"fl","c":{"a":0,"k":[1,1,1,1],"ix":4},"o":{"a":0,"k":100,"ix":5},"r":1,"bm":0,"nm":"Relleno 1","mn":"ADBE Vector Graphic - Fill","hd":false},{"ty":"tr","p":{"a":0,"k":[-15.5,-10.5],"ix":2},"a":{"a":0,"k":[0,0],"ix":1},"s":{"a":0,"k":[100,100],"ix":3},"r":{"a":0,"k":0,"ix":6},"o":{"a":0,"k":100,"ix":7},"sk":{"a":0,"k":0,"ix":4},"sa":{"a":0,"k":0,"ix":5},"nm":"Transformar"}],"nm":"Rectángulo 1","np":3,"cix":2,"bm":0,"ix":1,"mn":"ADBE Vector Group","hd":false}],"ip":129,"op":216,"st":0,"bm":0},{"ddd":0,"ind":26,"ty":4,"nm":"Capa de formas 11","sr":1,"ks":{"o":{"a":0,"k":100,"ix":11},"r":{"a":1,"k":[{"i":{"x":[0.667],"y":[1]},"o":{"x":[0.333],"y":[0]},"t":129,"s":[125.826]},{"t":179,"s":[338.826]}],"ix":10},"p":{"s":true,"x":{"a":1,"k":[{"i":{"x":[0.833],"y":[0.833]},"o":{"x":[0.167],"y":[0.167]},"t":128.692,"s":[197.075]},{"t":179,"s":[870.173]}],"ix":3},"y":{"a":1,"k":[{"i":{"x":[0.525],"y":[-1.612]},"o":{"x":[0.005],"y":[-0.285]},"t":129,"s":[682.78]},{"t":179,"s":[942.337]}],"ix":4}},"a":{"a":0,"k":[-15.375,-10.5,0],"ix":1},"s":{"a":0,"k":[155,155,100],"ix":6}},"ao":0,"shapes":[{"ty":"gr","it":[{"ty":"rc","d":1,"s":{"a":0,"k":[11,11],"ix":2},"p":{"a":0,"k":[0,0],"ix":3},"r":{"a":0,"k":0,"ix":4},"nm":"Trazado de rectángulo 1","mn":"ADBE Vector Shape - Rect","hd":false},{"ty":"fl","c":{"a":0,"k":[1,1,1,1],"ix":4},"o":{"a":0,"k":100,"ix":5},"r":1,"bm":0,"nm":"Relleno 1","mn":"ADBE Vector Graphic - Fill","hd":false},{"ty":"tr","p":{"a":0,"k":[-15.5,-10.5],"ix":2},"a":{"a":0,"k":[0,0],"ix":1},"s":{"a":0,"k":[100,100],"ix":3},"r":{"a":0,"k":0,"ix":6},"o":{"a":0,"k":100,"ix":7},"sk":{"a":0,"k":0,"ix":4},"sa":{"a":0,"k":0,"ix":5},"nm":"Transformar"}],"nm":"Rectángulo 1","np":3,"cix":2,"bm":0,"ix":1,"mn":"ADBE Vector Group","hd":false}],"ip":129,"op":216,"st":0,"bm":0},{"ddd":0,"ind":27,"ty":4,"nm":"Capa de formas 10","sr":1,"ks":{"o":{"a":0,"k":100,"ix":11},"r":{"a":1,"k":[{"i":{"x":[0.667],"y":[1]},"o":{"x":[0.333],"y":[0]},"t":129,"s":[-136.534]},{"t":179,"s":[76.466]}],"ix":10},"p":{"s":true,"x":{"a":1,"k":[{"i":{"x":[0.833],"y":[0.833]},"o":{"x":[0.167],"y":[0.167]},"t":128.692,"s":[197.075]},{"t":179,"s":[758.32]}],"ix":3},"y":{"a":1,"k":[{"i":{"x":[0.71],"y":[-1.69]},"o":{"x":[0.29],"y":[-1.555]},"t":129,"s":[682.78]},{"t":179,"s":[935.384]}],"ix":4}},"a":{"a":0,"k":[-15.375,-10.5,0],"ix":1},"s":{"a":0,"k":[155,155,100],"ix":6}},"ao":0,"shapes":[{"ty":"gr","it":[{"ty":"rc","d":1,"s":{"a":0,"k":[11,11],"ix":2},"p":{"a":0,"k":[0,0],"ix":3},"r":{"a":0,"k":0,"ix":4},"nm":"Trazado de rectángulo 1","mn":"ADBE Vector Shape - Rect","hd":false},{"ty":"fl","c":{"a":0,"k":[1,1,1,1],"ix":4},"o":{"a":0,"k":100,"ix":5},"r":1,"bm":0,"nm":"Relleno 1","mn":"ADBE Vector Graphic - Fill","hd":false},{"ty":"tr","p":{"a":0,"k":[-15.5,-10.5],"ix":2},"a":{"a":0,"k":[0,0],"ix":1},"s":{"a":0,"k":[100,100],"ix":3},"r":{"a":0,"k":0,"ix":6},"o":{"a":0,"k":100,"ix":7},"sk":{"a":0,"k":0,"ix":4},"sa":{"a":0,"k":0,"ix":5},"nm":"Transformar"}],"nm":"Rectángulo 1","np":3,"cix":2,"bm":0,"ix":1,"mn":"ADBE Vector Group","hd":false}],"ip":129,"op":216,"st":0,"bm":0},{"ddd":0,"ind":28,"ty":4,"nm":"Capa de formas 9","sr":1,"ks":{"o":{"a":0,"k":100,"ix":11},"r":{"a":1,"k":[{"i":{"x":[0.667],"y":[1]},"o":{"x":[0.333],"y":[0]},"t":129,"s":[0]},{"t":179,"s":[213]}],"ix":10},"p":{"s":true,"x":{"a":1,"k":[{"i":{"x":[0.833],"y":[0.833]},"o":{"x":[0.167],"y":[0.167]},"t":128.692,"s":[197.075]},{"t":179,"s":[921.01]}],"ix":3},"y":{"a":1,"k":[{"i":{"x":[0.371],"y":[-2.227]},"o":{"x":[0.273],"y":[-1.508]},"t":129,"s":[682.78]},{"t":179,"s":[818.28]}],"ix":4}},"a":{"a":0,"k":[-15.375,-10.5,0],"ix":1},"s":{"a":0,"k":[155,155,100],"ix":6}},"ao":0,"shapes":[{"ty":"gr","it":[{"ty":"rc","d":1,"s":{"a":0,"k":[11,11],"ix":2},"p":{"a":0,"k":[0,0],"ix":3},"r":{"a":0,"k":0,"ix":4},"nm":"Trazado de rectángulo 1","mn":"ADBE Vector Shape - Rect","hd":false},{"ty":"fl","c":{"a":0,"k":[1,1,1,1],"ix":4},"o":{"a":0,"k":100,"ix":5},"r":1,"bm":0,"nm":"Relleno 1","mn":"ADBE Vector Graphic - Fill","hd":false},{"ty":"tr","p":{"a":0,"k":[-15.5,-10.5],"ix":2},"a":{"a":0,"k":[0,0],"ix":1},"s":{"a":0,"k":[100,100],"ix":3},"r":{"a":0,"k":0,"ix":6},"o":{"a":0,"k":100,"ix":7},"sk":{"a":0,"k":0,"ix":4},"sa":{"a":0,"k":0,"ix":5},"nm":"Transformar"}],"nm":"Rectángulo 1","np":3,"cix":2,"bm":0,"ix":1,"mn":"ADBE Vector Group","hd":false}],"ip":129,"op":216,"st":0,"bm":0},{"ddd":0,"ind":29,"ty":4,"nm":"Capa de formas 8","sr":1,"ks":{"o":{"a":0,"k":100,"ix":11},"r":{"a":1,"k":[{"i":{"x":[0.667],"y":[1]},"o":{"x":[0.333],"y":[0]},"t":129,"s":[298.478]},{"t":179,"s":[511.478]}],"ix":10},"p":{"s":true,"x":{"a":1,"k":[{"i":{"x":[0.833],"y":[0.833]},"o":{"x":[0.167],"y":[0.167]},"t":128.692,"s":[197.075]},{"t":179,"s":[952.01]}],"ix":3},"y":{"a":1,"k":[{"i":{"x":[0.509],"y":[2.405]},"o":{"x":[0.044],"y":[0.375]},"t":129,"s":[682.78]},{"t":179,"s":[479.28]}],"ix":4}},"a":{"a":0,"k":[-15.375,-10.5,0],"ix":1},"s":{"a":0,"k":[155,155,100],"ix":6}},"ao":0,"shapes":[{"ty":"gr","it":[{"ty":"rc","d":1,"s":{"a":0,"k":[11,11],"ix":2},"p":{"a":0,"k":[0,0],"ix":3},"r":{"a":0,"k":0,"ix":4},"nm":"Trazado de rectángulo 1","mn":"ADBE Vector Shape - Rect","hd":false},{"ty":"fl","c":{"a":0,"k":[1,1,1,1],"ix":4},"o":{"a":0,"k":100,"ix":5},"r":1,"bm":0,"nm":"Relleno 1","mn":"ADBE Vector Graphic - Fill","hd":false},{"ty":"tr","p":{"a":0,"k":[-15.5,-10.5],"ix":2},"a":{"a":0,"k":[0,0],"ix":1},"s":{"a":0,"k":[100,100],"ix":3},"r":{"a":0,"k":0,"ix":6},"o":{"a":0,"k":100,"ix":7},"sk":{"a":0,"k":0,"ix":4},"sa":{"a":0,"k":0,"ix":5},"nm":"Transformar"}],"nm":"Rectángulo 1","np":3,"cix":2,"bm":0,"ix":1,"mn":"ADBE Vector Group","hd":false}],"ip":129,"op":216,"st":0,"bm":0},{"ddd":0,"ind":30,"ty":4,"nm":"Capa de formas 7","sr":1,"ks":{"o":{"a":0,"k":100,"ix":11},"r":{"a":1,"k":[{"i":{"x":[0.667],"y":[1]},"o":{"x":[0.333],"y":[0]},"t":129,"s":[525.218]},{"t":178.5380859375,"s":[738.218]}],"ix":10},"p":{"s":true,"x":{"a":1,"k":[{"i":{"x":[0.833],"y":[0.833]},"o":{"x":[0.167],"y":[0.167]},"t":128.692,"s":[197.075]},{"t":178.5380859375,"s":[921.01]}],"ix":3},"y":{"a":1,"k":[{"i":{"x":[0.525],"y":[-3.958]},"o":{"x":[0.29],"y":[-2.872]},"t":129,"s":[682.78]},{"t":178.5380859375,"s":[818.28]}],"ix":4}},"a":{"a":0,"k":[-15.375,-10.5,0],"ix":1},"s":{"a":0,"k":[155,155,100],"ix":6}},"ao":0,"shapes":[{"ty":"gr","it":[{"ty":"rc","d":1,"s":{"a":0,"k":[11,11],"ix":2},"p":{"a":0,"k":[0,0],"ix":3},"r":{"a":0,"k":0,"ix":4},"nm":"Trazado de rectángulo 1","mn":"ADBE Vector Shape - Rect","hd":false},{"ty":"fl","c":{"a":0,"k":[1,1,1,1],"ix":4},"o":{"a":0,"k":100,"ix":5},"r":1,"bm":0,"nm":"Relleno 1","mn":"ADBE Vector Graphic - Fill","hd":false},{"ty":"tr","p":{"a":0,"k":[-15.5,-10.5],"ix":2},"a":{"a":0,"k":[0,0],"ix":1},"s":{"a":0,"k":[100,100],"ix":3},"r":{"a":0,"k":0,"ix":6},"o":{"a":0,"k":100,"ix":7},"sk":{"a":0,"k":0,"ix":4},"sa":{"a":0,"k":0,"ix":5},"nm":"Transformar"}],"nm":"Rectángulo 1","np":3,"cix":2,"bm":0,"ix":1,"mn":"ADBE Vector Group","hd":false}],"ip":129,"op":216,"st":0,"bm":0},{"ddd":0,"ind":31,"ty":4,"nm":"Capa de formas 6","sr":1,"ks":{"o":{"a":0,"k":100,"ix":11},"r":{"a":0,"k":0,"ix":10},"p":{"a":0,"k":[450,450,0],"ix":2},"a":{"a":0,"k":[0,0,0],"ix":1},"s":{"a":0,"k":[33,33,100],"ix":6}},"ao":0,"shapes":[{"ty":"gr","it":[{"ind":0,"ty":"sh","ix":1,"ks":{"a":0,"k":{"i":[[150,0],[0,-85],[0,-200],[0,365],[150,0],[0,-51]],"o":[[-150,0],[0,365],[0,-200],[0,-85],[-150,0],[0,-51]],"v":[[-200,-350],[-400,-165],[0,415.854],[400,-165],[200,-350],[0,-199]],"c":true},"ix":2},"nm":"Trazado 1","mn":"ADBE Vector Shape - Group","hd":false},{"ty":"st","c":{"a":0,"k":[1,1,1,1],"ix":3},"o":{"a":0,"k":100,"ix":4},"w":{"a":0,"k":70,"ix":5},"lc":2,"lj":2,"bm":0,"nm":"Trazo 1","mn":"ADBE Vector Graphic - Stroke","hd":false},{"ty":"tr","p":{"a":0,"k":[0,0],"ix":2},"a":{"a":0,"k":[0,0],"ix":1},"s":{"a":0,"k":[100,100],"ix":3},"r":{"a":0,"k":0,"ix":6},"o":{"a":0,"k":100,"ix":7},"sk":{"a":0,"k":0,"ix":4},"sa":{"a":0,"k":0,"ix":5},"nm":"Transformar"}],"nm":"Forma 1","np":3,"cix":2,"bm":0,"ix":1,"mn":"ADBE Vector Group","hd":false},{"ty":"tm","s":{"a":1,"k":[{"i":{"x":[0.833],"y":[0.833]},"o":{"x":[0.167],"y":[0.167]},"t":174,"s":[0]},{"i":{"x":[0.833],"y":[0.833]},"o":{"x":[0.167],"y":[0.167]},"t":196,"s":[100]},{"t":261,"s":[100]}],"ix":1},"e":{"a":1,"k":[{"i":{"x":[0.833],"y":[0.833]},"o":{"x":[0.167],"y":[0.167]},"t":204,"s":[0]},{"t":215,"s":[100]}],"ix":2},"o":{"a":0,"k":-33,"ix":3},"m":2,"ix":2,"nm":"Recortar trazados 1","mn":"ADBE Vector Filter - Trim","hd":false}],"ip":172,"op":261,"st":86,"bm":0},{"ddd":0,"ind":32,"ty":4,"nm":"Capa de formas 5","sr":1,"ks":{"o":{"a":0,"k":100,"ix":11},"r":{"a":1,"k":[{"i":{"x":[0.208],"y":[1]},"o":{"x":[0.526],"y":[0]},"t":54,"s":[61]},{"t":126,"s":[-43.523]}],"ix":10},"p":{"a":1,"k":[{"i":{"x":0,"y":1},"o":{"x":0.691,"y":0},"t":119,"s":[912,896.277,0],"to":[-5,-1.667,0],"ti":[-27.03,-31.239,0]},{"i":{"x":0.667,"y":1},"o":{"x":1,"y":0},"t":139,"s":[882,886.277,0],"to":[27.03,31.239,0],"ti":[-32.03,-32.905,0]},{"t":190,"s":[1074.182,1083.709,0]}],"ix":2},"a":{"a":0,"k":[-300,247,0],"ix":1},"s":{"a":0,"k":[-100,100,100],"ix":6}},"ao":0,"shapes":[{"ty":"gr","it":[{"ind":0,"ty":"sh","ix":1,"ks":{"a":0,"k":{"i":[[0,0],[0,0]],"o":[[0,0],[0,0]],"v":[[-289.5,181.5],[-310,181.5]],"c":false},"ix":2},"nm":"Trazado 1","mn":"ADBE Vector Shape - Group","hd":false},{"ty":"st","c":{"a":0,"k":[1,1,1,1],"ix":3},"o":{"a":0,"k":100,"ix":4},"w":{"a":0,"k":10,"ix":5},"lc":1,"lj":1,"ml":4,"bm":0,"nm":"Trazo 1","mn":"ADBE Vector Graphic - Stroke","hd":false},{"ty":"tr","p":{"a":0,"k":[0,0],"ix":2},"a":{"a":0,"k":[0,0],"ix":1},"s":{"a":0,"k":[100,100],"ix":3},"r":{"a":0,"k":0,"ix":6},"o":{"a":0,"k":100,"ix":7},"sk":{"a":0,"k":0,"ix":4},"sa":{"a":0,"k":0,"ix":5},"nm":"Transformar"}],"nm":"Forma 5","np":3,"cix":2,"bm":0,"ix":1,"mn":"ADBE Vector Group","hd":false},{"ty":"gr","it":[{"ind":0,"ty":"sh","ix":1,"ks":{"a":0,"k":{"i":[[0,0],[0,0]],"o":[[0,0],[0,0]],"v":[[-280,135.5],[-318.5,135.5]],"c":false},"ix":2},"nm":"Trazado 1","mn":"ADBE Vector Shape - Group","hd":false},{"ty":"st","c":{"a":0,"k":[1,1,1,1],"ix":3},"o":{"a":0,"k":100,"ix":4},"w":{"a":0,"k":15,"ix":5},"lc":1,"lj":1,"ml":4,"bm":0,"nm":"Trazo 1","mn":"ADBE Vector Graphic - Stroke","hd":false},{"ty":"tr","p":{"a":0,"k":[0,0],"ix":2},"a":{"a":0,"k":[0,0],"ix":1},"s":{"a":0,"k":[100,100],"ix":3},"r":{"a":0,"k":0,"ix":6},"o":{"a":0,"k":100,"ix":7},"sk":{"a":0,"k":0,"ix":4},"sa":{"a":0,"k":0,"ix":5},"nm":"Transformar"}],"nm":"Forma 4","np":3,"cix":2,"bm":0,"ix":2,"mn":"ADBE Vector Group","hd":false},{"ty":"gr","it":[{"ind":0,"ty":"sh","ix":1,"ks":{"a":0,"k":{"i":[[0,0],[0,0]],"o":[[0,0],[0,0]],"v":[[-268.5,88.5],[-329,88.5]],"c":false},"ix":2},"nm":"Trazado 1","mn":"ADBE Vector Shape - Group","hd":false},{"ty":"st","c":{"a":0,"k":[1,1,1,1],"ix":3},"o":{"a":0,"k":100,"ix":4},"w":{"a":0,"k":15,"ix":5},"lc":1,"lj":1,"ml":4,"bm":0,"nm":"Trazo 1","mn":"ADBE Vector Graphic - Stroke","hd":false},{"ty":"tr","p":{"a":0,"k":[0,0],"ix":2},"a":{"a":0,"k":[0,0],"ix":1},"s":{"a":0,"k":[100,100],"ix":3},"r":{"a":0,"k":0,"ix":6},"o":{"a":0,"k":100,"ix":7},"sk":{"a":0,"k":0,"ix":4},"sa":{"a":0,"k":0,"ix":5},"nm":"Transformar"}],"nm":"Forma 3","np":3,"cix":2,"bm":0,"ix":3,"mn":"ADBE Vector Group","hd":false},{"ty":"gr","it":[{"ind":0,"ty":"sh","ix":1,"ks":{"a":0,"k":{"i":[[-2,0.5],[0,0]],"o":[[2,-0.5],[0,0]],"v":[[-261.5,45],[-336.5,45]],"c":true},"ix":2},"nm":"Trazado 1","mn":"ADBE Vector Shape - Group","hd":false},{"ty":"st","c":{"a":0,"k":[1,1,1,1],"ix":3},"o":{"a":0,"k":100,"ix":4},"w":{"a":0,"k":15,"ix":5},"lc":1,"lj":1,"ml":4,"bm":0,"nm":"Trazo 1","mn":"ADBE Vector Graphic - Stroke","hd":false},{"ty":"tr","p":{"a":0,"k":[0,0],"ix":2},"a":{"a":0,"k":[0,0],"ix":1},"s":{"a":0,"k":[100,100],"ix":3},"r":{"a":0,"k":0,"ix":6},"o":{"a":0,"k":100,"ix":7},"sk":{"a":0,"k":0,"ix":4},"sa":{"a":0,"k":0,"ix":5},"nm":"Transformar"}],"nm":"Forma 2","np":3,"cix":2,"bm":0,"ix":4,"mn":"ADBE Vector Group","hd":false},{"ty":"gr","it":[{"ind":0,"ty":"sh","ix":1,"ks":{"a":0,"k":{"i":[[0,0],[-3,-2],[-2.516,-12.322],[0,0]],"o":[[0,0],[0.517,0.345],[12.088,59.204],[0,0]],"v":[[-250,0],[-347,2],[-342.234,22.252],[-300,250]],"c":true},"ix":2},"nm":"Trazado 1","mn":"ADBE Vector Shape - Group","hd":false},{"ty":"st","c":{"a":0,"k":[1,1,1,1],"ix":3},"o":{"a":0,"k":100,"ix":4},"w":{"a":0,"k":20,"ix":5},"lc":2,"lj":2,"bm":0,"nm":"Trazo 1","mn":"ADBE Vector Graphic - Stroke","hd":false},{"ty":"tr","p":{"a":0,"k":[0,0],"ix":2},"a":{"a":0,"k":[0,0],"ix":1},"s":{"a":0,"k":[100,100],"ix":3},"r":{"a":0,"k":0,"ix":6},"o":{"a":0,"k":100,"ix":7},"sk":{"a":0,"k":0,"ix":4},"sa":{"a":0,"k":0,"ix":5},"nm":"Transformar"}],"nm":"Forma 1","np":3,"cix":2,"bm":0,"ix":5,"mn":"ADBE Vector Group","hd":false}],"ip":54,"op":191,"st":11,"bm":0},{"ddd":0,"ind":33,"ty":4,"nm":"Capa de formas 4","sr":1,"ks":{"o":{"a":0,"k":100,"ix":11},"r":{"a":1,"k":[{"i":{"x":[0.208],"y":[1]},"o":{"x":[0.526],"y":[0]},"t":54,"s":[-61]},{"t":126,"s":[43.523]}],"ix":10},"p":{"a":1,"k":[{"i":{"x":0,"y":1},"o":{"x":0.691,"y":0},"t":119,"s":[-12,892.277,0],"to":[5,-1.667,0],"ti":[27.38,-32.114,0]},{"i":{"x":0.667,"y":1},"o":{"x":1,"y":0},"t":139,"s":[18,882.277,0],"to":[-27.38,32.114,0],"ti":[32.38,-33.781,0]},{"t":190,"s":[-176.282,1084.96,0]}],"ix":2},"a":{"a":0,"k":[-300,247,0],"ix":1},"s":{"a":0,"k":[100,100,100],"ix":6}},"ao":0,"shapes":[{"ty":"gr","it":[{"ind":0,"ty":"sh","ix":1,"ks":{"a":0,"k":{"i":[[0,0],[0,0]],"o":[[0,0],[0,0]],"v":[[-289.5,181.5],[-310,181.5]],"c":false},"ix":2},"nm":"Trazado 1","mn":"ADBE Vector Shape - Group","hd":false},{"ty":"st","c":{"a":0,"k":[1,1,1,1],"ix":3},"o":{"a":0,"k":100,"ix":4},"w":{"a":0,"k":15,"ix":5},"lc":1,"lj":1,"ml":4,"bm":0,"nm":"Trazo 1","mn":"ADBE Vector Graphic - Stroke","hd":false},{"ty":"tr","p":{"a":0,"k":[0,0],"ix":2},"a":{"a":0,"k":[0,0],"ix":1},"s":{"a":0,"k":[100,100],"ix":3},"r":{"a":0,"k":0,"ix":6},"o":{"a":0,"k":100,"ix":7},"sk":{"a":0,"k":0,"ix":4},"sa":{"a":0,"k":0,"ix":5},"nm":"Transformar"}],"nm":"Forma 5","np":3,"cix":2,"bm":0,"ix":1,"mn":"ADBE Vector Group","hd":false},{"ty":"gr","it":[{"ind":0,"ty":"sh","ix":1,"ks":{"a":0,"k":{"i":[[0,0],[0,0]],"o":[[0,0],[0,0]],"v":[[-280,135.5],[-318.5,135.5]],"c":false},"ix":2},"nm":"Trazado 1","mn":"ADBE Vector Shape - Group","hd":false},{"ty":"st","c":{"a":0,"k":[1,1,1,1],"ix":3},"o":{"a":0,"k":100,"ix":4},"w":{"a":0,"k":15,"ix":5},"lc":1,"lj":1,"ml":4,"bm":0,"nm":"Trazo 1","mn":"ADBE Vector Graphic - Stroke","hd":false},{"ty":"tr","p":{"a":0,"k":[0,0],"ix":2},"a":{"a":0,"k":[0,0],"ix":1},"s":{"a":0,"k":[100,100],"ix":3},"r":{"a":0,"k":0,"ix":6},"o":{"a":0,"k":100,"ix":7},"sk":{"a":0,"k":0,"ix":4},"sa":{"a":0,"k":0,"ix":5},"nm":"Transformar"}],"nm":"Forma 4","np":3,"cix":2,"bm":0,"ix":2,"mn":"ADBE Vector Group","hd":false},{"ty":"gr","it":[{"ind":0,"ty":"sh","ix":1,"ks":{"a":0,"k":{"i":[[0,0],[0,0]],"o":[[0,0],[0,0]],"v":[[-268.5,88.5],[-329,88.5]],"c":false},"ix":2},"nm":"Trazado 1","mn":"ADBE Vector Shape - Group","hd":false},{"ty":"st","c":{"a":0,"k":[1,1,1,1],"ix":3},"o":{"a":0,"k":100,"ix":4},"w":{"a":0,"k":15,"ix":5},"lc":1,"lj":1,"ml":4,"bm":0,"nm":"Trazo 1","mn":"ADBE Vector Graphic - Stroke","hd":false},{"ty":"tr","p":{"a":0,"k":[0,0],"ix":2},"a":{"a":0,"k":[0,0],"ix":1},"s":{"a":0,"k":[100,100],"ix":3},"r":{"a":0,"k":0,"ix":6},"o":{"a":0,"k":100,"ix":7},"sk":{"a":0,"k":0,"ix":4},"sa":{"a":0,"k":0,"ix":5},"nm":"Transformar"}],"nm":"Forma 3","np":3,"cix":2,"bm":0,"ix":3,"mn":"ADBE Vector Group","hd":false},{"ty":"gr","it":[{"ind":0,"ty":"sh","ix":1,"ks":{"a":0,"k":{"i":[[-2,0.5],[0,0]],"o":[[2,-0.5],[0,0]],"v":[[-261.5,45],[-336.5,45]],"c":true},"ix":2},"nm":"Trazado 1","mn":"ADBE Vector Shape - Group","hd":false},{"ty":"st","c":{"a":0,"k":[1,1,1,1],"ix":3},"o":{"a":0,"k":100,"ix":4},"w":{"a":0,"k":15,"ix":5},"lc":1,"lj":1,"ml":4,"bm":0,"nm":"Trazo 1","mn":"ADBE Vector Graphic - Stroke","hd":false},{"ty":"tr","p":{"a":0,"k":[0,0],"ix":2},"a":{"a":0,"k":[0,0],"ix":1},"s":{"a":0,"k":[100,100],"ix":3},"r":{"a":0,"k":0,"ix":6},"o":{"a":0,"k":100,"ix":7},"sk":{"a":0,"k":0,"ix":4},"sa":{"a":0,"k":0,"ix":5},"nm":"Transformar"}],"nm":"Forma 2","np":3,"cix":2,"bm":0,"ix":4,"mn":"ADBE Vector Group","hd":false},{"ty":"gr","it":[{"ind":0,"ty":"sh","ix":1,"ks":{"a":0,"k":{"i":[[0,0],[-3,-2],[-2.516,-12.322],[0,0]],"o":[[0,0],[0.517,0.345],[12.088,59.204],[0,0]],"v":[[-250,0],[-347,2],[-342.234,22.252],[-300,250]],"c":true},"ix":2},"nm":"Trazado 1","mn":"ADBE Vector Shape - Group","hd":false},{"ty":"st","c":{"a":0,"k":[1,1,1,1],"ix":3},"o":{"a":0,"k":100,"ix":4},"w":{"a":0,"k":21,"ix":5},"lc":2,"lj":2,"bm":0,"nm":"Trazo 1","mn":"ADBE Vector Graphic - Stroke","hd":false},{"ty":"tr","p":{"a":0,"k":[0,0],"ix":2},"a":{"a":0,"k":[0,0],"ix":1},"s":{"a":0,"k":[100,100],"ix":3},"r":{"a":0,"k":0,"ix":6},"o":{"a":0,"k":100,"ix":7},"sk":{"a":0,"k":0,"ix":4},"sa":{"a":0,"k":0,"ix":5},"nm":"Transformar"}],"nm":"Forma 1","np":3,"cix":2,"bm":0,"ix":5,"mn":"ADBE Vector Group","hd":false}],"ip":54,"op":191,"st":11,"bm":0},{"ddd":0,"ind":34,"ty":4,"nm":"Capa de formas 2","parent":36,"sr":1,"ks":{"o":{"a":0,"k":100,"ix":11},"r":{"a":0,"k":0,"ix":10},"p":{"a":0,"k":[0.003,28.942,0],"ix":2},"a":{"a":0,"k":[0,0,0],"ix":1},"s":{"a":0,"k":[100,100,100],"ix":6}},"ao":0,"shapes":[{"ty":"gr","it":[{"ind":0,"ty":"sh","ix":1,"ks":{"a":1,"k":[{"i":{"x":0.667,"y":1},"o":{"x":0.333,"y":0},"t":0,"s":[{"i":[[0,0],[-35.003,-62.942],[19,-26]],"o":[[0,0],[34.398,61.854],[-19,26]],"v":[[0,173],[-15,301],[-13,453]],"c":false}]},{"i":{"x":0.667,"y":1},"o":{"x":0.333,"y":0},"t":67.878,"s":[{"i":[[0,0],[31.383,-42.359],[19,-26]],"o":[[0,0],[-42.132,56.868],[-19,26]],"v":[[0,173],[-15,301],[-13,453]],"c":false}]},{"i":{"x":0.833,"y":0.833},"o":{"x":0.333,"y":0},"t":107.611,"s":[{"i":[[0,0],[-15,-27],[19,-26]],"o":[[0,0],[15,27],[-19,26]],"v":[[0,173],[-15,301],[-13,453]],"c":false}]},{"t":215,"s":[{"i":[[0,0],[12.551,-31.089],[19,-26]],"o":[[0,0],[-18.454,31.262],[-19,26]],"v":[[0,173],[-33.914,306.59],[-72.659,460.799]],"c":false}]}],"ix":2},"nm":"Trazado 1","mn":"ADBE Vector Shape - Group","hd":false},{"ty":"st","c":{"a":0,"k":[1,1,1,1],"ix":3},"o":{"a":0,"k":100,"ix":4},"w":{"a":0,"k":9,"ix":5},"lc":1,"lj":1,"ml":4,"bm":0,"nm":"Trazo 1","mn":"ADBE Vector Graphic - Stroke","hd":false},{"ty":"tr","p":{"a":0,"k":[0,0],"ix":2},"a":{"a":0,"k":[0,0],"ix":1},"s":{"a":0,"k":[100,100],"ix":3},"r":{"a":0,"k":0,"ix":6},"o":{"a":0,"k":100,"ix":7},"sk":{"a":0,"k":0,"ix":4},"sa":{"a":0,"k":0,"ix":5},"nm":"Transformar"}],"nm":"Forma 1","np":3,"cix":2,"bm":0,"ix":1,"mn":"ADBE Vector Group","hd":false},{"ty":"tm","s":{"a":1,"k":[{"i":{"x":[0.827],"y":[1]},"o":{"x":[1],"y":[0]},"t":165,"s":[0]},{"t":176,"s":[0]}],"ix":1},"e":{"a":1,"k":[{"i":{"x":[0.827],"y":[1]},"o":{"x":[0.805],"y":[0.466]},"t":165,"s":[100]},{"t":176,"s":[0]}],"ix":2},"o":{"a":0,"k":0,"ix":3},"m":1,"ix":2,"nm":"Recortar trazados 1","mn":"ADBE Vector Filter - Trim","hd":false}],"ip":0,"op":187,"st":0,"bm":0},{"ddd":0,"ind":35,"ty":4,"nm":"Capa de formas 3","sr":1,"ks":{"o":{"a":0,"k":100,"ix":11},"r":{"a":1,"k":[{"i":{"x":[0.508],"y":[1.182]},"o":{"x":[0.334],"y":[-0.047]},"t":0,"s":[0]},{"i":{"x":[0.519],"y":[1.008]},"o":{"x":[0.77],"y":[0.195]},"t":32.283,"s":[14.04]},{"i":{"x":[0],"y":[1.006]},"o":{"x":[0.307],"y":[0.007]},"t":71.188,"s":[-10.013]},{"i":{"x":[0.833],"y":[1]},"o":{"x":[0.765],"y":[-0.122]},"t":107.611,"s":[0]},{"t":149,"s":[16]}],"ix":10},"p":{"s":true,"x":{"a":1,"k":[{"i":{"x":[0.667],"y":[1]},"o":{"x":[0.186],"y":[-0.014]},"t":0,"s":[450]},{"i":{"x":[0.667],"y":[1]},"o":{"x":[0.621],"y":[0]},"t":29.8,"s":[474]},{"i":{"x":[0.667],"y":[1]},"o":{"x":[0.584],"y":[-0.003]},"t":59.6,"s":[434]},{"t":107.9765625,"s":[450]}],"ix":3},"y":{"a":1,"k":[{"i":{"x":[0.702],"y":[0.865]},"o":{"x":[0.186],"y":[0.002]},"t":0,"s":[1201.5]},{"i":{"x":[0.729],"y":[0.748]},"o":{"x":[0.597],"y":[0.418]},"t":29.8,"s":[990.833]},{"i":{"x":[0.377],"y":[0.918]},"o":{"x":[0.553],"y":[0.884]},"t":59.6,"s":[780.167]},{"i":{"x":[0.833],"y":[1]},"o":{"x":[0.371],"y":[0.544]},"t":107.977,"s":[569.5]},{"t":215,"s":[518.5]}],"ix":4}},"a":{"a":0,"k":[0,148.5,0],"ix":1},"s":{"a":0,"k":[100,100,100],"ix":6}},"ao":0,"shapes":[{"ind":0,"ty":"sh","ix":1,"ks":{"a":0,"k":{"i":[[-55.228,0],[0,-82.843],[49.087,-9.558],[0.662,-13.503],[15.116,2.176],[4.786,0],[3.671,-0.592],[0.245,4.032],[3.218,0.635],[0,76.148]],"o":[[55.228,0],[0,76.235],[-3.366,0.655],[-0.207,4.218],[-3.669,-0.528],[-5.174,0],[-13.711,2.212],[-0.817,-13.457],[-49.006,-9.668],[0,-82.843]],"v":[[0,-133.5],[100,0],[12.999,148.744],[34.022,199.995],[12.659,196.881],[0,203],[-13.21,196.998],[-31.182,199.988],[-13.167,148.711],[-100,0]],"c":true},"ix":2},"nm":"Trazado 1","mn":"ADBE Vector Shape - Group","hd":false},{"ty":"tm","s":{"a":1,"k":[{"i":{"x":[0.833],"y":[0.833]},"o":{"x":[0.167],"y":[0.167]},"t":124.089,"s":[8]},{"i":{"x":[0.833],"y":[0.833]},"o":{"x":[0.167],"y":[0.167]},"t":138.161,"s":[4]},{"i":{"x":[0.833],"y":[0.833]},"o":{"x":[0.167],"y":[0.167]},"t":149,"s":[0]},{"i":{"x":[0.827],"y":[1]},"o":{"x":[0.895],"y":[0.516]},"t":165,"s":[0]},{"t":176,"s":[46]}],"ix":1},"e":{"a":1,"k":[{"i":{"x":[0.833],"y":[0.833]},"o":{"x":[0.167],"y":[0.167]},"t":115.889,"s":[49]},{"i":{"x":[0.833],"y":[0.833]},"o":{"x":[0.167],"y":[0.167]},"t":130,"s":[47]},{"i":{"x":[0.833],"y":[0.833]},"o":{"x":[0.167],"y":[0.167]},"t":149,"s":[46]},{"t":165,"s":[46]}],"ix":2},"o":{"a":0,"k":-28,"ix":3},"m":1,"ix":2,"nm":"Recortar trazados 1","mn":"ADBE Vector Filter - Trim","hd":false},{"ty":"st","c":{"a":0,"k":[1,1,1,1],"ix":3},"o":{"a":0,"k":100,"ix":4},"w":{"a":0,"k":15,"ix":5},"lc":2,"lj":1,"ml":1,"bm":0,"nm":"Trazo 1","mn":"ADBE Vector Graphic - Stroke","hd":false}],"ip":108,"op":187,"st":0,"bm":0},{"ddd":0,"ind":36,"ty":4,"nm":"Capa de formas 1","sr":1,"ks":{"o":{"a":0,"k":100,"ix":11},"r":{"a":1,"k":[{"i":{"x":[0.508],"y":[1.182]},"o":{"x":[0.334],"y":[-0.047]},"t":0,"s":[0]},{"i":{"x":[0.519],"y":[1.008]},"o":{"x":[0.77],"y":[0.195]},"t":32.283,"s":[14.04]},{"i":{"x":[0],"y":[1.006]},"o":{"x":[0.307],"y":[0.007]},"t":71.188,"s":[-10.013]},{"i":{"x":[0.833],"y":[1]},"o":{"x":[0.765],"y":[0.14]},"t":107.611,"s":[0]},{"t":149,"s":[-14]}],"ix":10},"p":{"s":true,"x":{"a":1,"k":[{"i":{"x":[0.667],"y":[1]},"o":{"x":[0.186],"y":[-0.014]},"t":0,"s":[450]},{"i":{"x":[0.667],"y":[1]},"o":{"x":[0.621],"y":[0]},"t":29.8,"s":[474]},{"i":{"x":[0.667],"y":[1]},"o":{"x":[0.584],"y":[-0.003]},"t":59.6,"s":[434]},{"t":107.9765625,"s":[450]}],"ix":3},"y":{"a":1,"k":[{"i":{"x":[0.702],"y":[0.865]},"o":{"x":[0.186],"y":[0.002]},"t":0,"s":[1201.5]},{"i":{"x":[0.729],"y":[0.748]},"o":{"x":[0.597],"y":[0.418]},"t":29.8,"s":[990.833]},{"i":{"x":[0.325],"y":[0.841]},"o":{"x":[0.553],"y":[0.884]},"t":59.6,"s":[780.167]},{"i":{"x":[0.833],"y":[1]},"o":{"x":[0.371],"y":[0.544]},"t":107.977,"s":[569.5]},{"t":215,"s":[518.5]}],"ix":4}},"a":{"a":0,"k":[0,148.5,0],"ix":1},"s":{"a":0,"k":[100,100,100],"ix":6}},"ao":0,"shapes":[{"ind":0,"ty":"sh","ix":1,"ks":{"a":0,"k":{"i":[[-55.228,0],[0,-82.843],[49.087,-9.558],[0.662,-13.503],[15.116,2.176],[4.786,0],[3.671,-0.592],[0.245,4.032],[3.218,0.635],[0,76.148]],"o":[[55.228,0],[0,76.235],[-3.366,0.655],[-0.207,4.218],[-3.669,-0.528],[-5.174,0],[-13.711,2.212],[-0.817,-13.457],[-49.006,-9.668],[0,-82.843]],"v":[[0,-133.5],[100,0],[12.999,148.744],[34.022,199.995],[12.659,196.881],[0,203],[-13.21,196.998],[-31.182,199.988],[-13.167,148.711],[-100,0]],"c":true},"ix":2},"nm":"Trazado 1","mn":"ADBE Vector Shape - Group","hd":false},{"ty":"tm","s":{"a":1,"k":[{"i":{"x":[0.827],"y":[1]},"o":{"x":[0.646],"y":[0.377]},"t":165,"s":[0]},{"t":176,"s":[50]}],"ix":1},"e":{"a":1,"k":[{"i":{"x":[0.827],"y":[1]},"o":{"x":[0.805],"y":[0.466]},"t":165,"s":[100]},{"t":176,"s":[50]}],"ix":2},"o":{"a":0,"k":0,"ix":3},"m":1,"ix":2,"nm":"Recortar trazados 1","mn":"ADBE Vector Filter - Trim","hd":false},{"ty":"st","c":{"a":0,"k":[1,1,1,1],"ix":3},"o":{"a":0,"k":100,"ix":4},"w":{"a":0,"k":15,"ix":5},"lc":1,"lj":1,"ml":4,"bm":0,"nm":"Trazo 1","mn":"ADBE Vector Graphic - Stroke","hd":false}],"ip":0,"op":187,"st":0,"bm":0}],"markers":[{"tm":36,"cm":"","dr":0},{"tm":72,"cm":"","dr":0},{"tm":130,"cm":"","dr":0}]}